catholic_mass_readings-0.6.0.dist-info/METADATA
catholic_mass_readings-0.6.0.dist-info/WHEEL
catholic_mass_readings-0.6.0.dist-info/entry_points.txt
catholic_mass_readings-0.6.0.dist-info/licenses/LICENSE
catholic_mass_readings/__init__.py
catholic_mass_readings/__main__.py
catholic_mass_readings/commands/__init__.py
catholic_mass_readings/commands/common.py
catholic_mass_readings/commands/mass.py
catholic_mass_readings/constants.py
catholic_mass_readings/models.py
catholic_mass_readings/py.typed
catholic_mass_readings/usccb.py
catholic_mass_readings/utils.py
catholic_mass_readings-0.6.0.dist-info/RECORD
