Metadata-Version: 2.1
Name: catholic-mass-readings
Version: 0.6.0
Summary: Provides an API for scraping the web page from https://bible.usccb.org/bible/readings/ to get the readings
Keywords: catholic,daily,lecture,mass,readings,scripture,usccb
Author-Email: Robert Colfin <robert.m.colfin@gmail.com>
License: Apache
Classifier: Development Status :: 4 - Beta
Classifier: Intended Audience :: Developers
Classifier: License :: OSI Approved :: Apache Software License
Classifier: Natural Language :: English
Classifier: Operating System :: OS Independent
Classifier: Programming Language :: Python :: 3.8
Classifier: Programming Language :: Python :: 3.9
Classifier: Programming Language :: Python :: 3.10
Classifier: Programming Language :: Python :: 3.11
Classifier: Programming Language :: Python :: 3.12
Classifier: Programming Language :: Python :: 3.13
Requires-Python: <4.0,>=3.8
Requires-Dist: bs4<1.0.0,>=0.0.2
Requires-Dist: aiofiles<25.0.0,>=24.1.0
Requires-Dist: curl-cffi>=0.9.0
Requires-Dist: asyncclick<9.0.0.0,>=8.1.7.2
Requires-Dist: html5lib<2.0,>=1.1
Requires-Dist: pytz<2026.0,>=2024.2
